package com.google.android.gms.ads.internal.reward.client;

import android.os.IBinder;
import android.os.Parcel;
import android.os.RemoteException;

class zzd$zza$zza
  implements zzd
{
  private IBinder zznJ;
  
  zzd$zza$zza(IBinder paramIBinder)
  {
    zznJ = paramIBinder;
  }
  
  public IBinder asBinder()
  {
    return zznJ;
  }
  
  public void onRewardedVideoAdClosed()
    throws RemoteException
  {
    Parcel localParcel1 = Parcel.obtain();
    Parcel localParcel2 = Parcel.obtain();
    try
    {
      localParcel1.writeInterfaceToken("com.google.android.gms.ads.internal.reward.client.IRewardedVideoAdListener");
      zznJ.transact(4, localParcel1, localParcel2, 0);
      localParcel2.readException();
      return;
    }
    finally
    {
      localParcel2.recycle();
      localParcel1.recycle();
    }
  }
  
  public void onRewardedVideoAdFailedToLoad(int paramInt)
    throws RemoteException
  {
    Parcel localParcel1 = Parcel.obtain();
    Parcel localParcel2 = Parcel.obtain();
    try
    {
      localParcel1.writeInterfaceToken("com.google.android.gms.ads.internal.reward.client.IRewardedVideoAdListener");
      localParcel1.writeInt(paramInt);
      zznJ.transact(7, localParcel1, localParcel2, 0);
      localParcel2.readException();
      return;
    }
    finally
    {
      localParcel2.recycle();
      localParcel1.recycle();
    }
  }
  
  public void onRewardedVideoAdLeftApplication()
    throws RemoteException
  {
    Parcel localParcel1 = Parcel.obtain();
    Parcel localParcel2 = Parcel.obtain();
    try
    {
      localParcel1.writeInterfaceToken("com.google.android.gms.ads.internal.reward.client.IRewardedVideoAdListener");
      zznJ.transact(6, localParcel1, localParcel2, 0);
      localParcel2.readException();
      return;
    }
    finally
    {
      localParcel2.recycle();
      localParcel1.recycle();
    }
  }
  
  public void onRewardedVideoAdLoaded()
    throws RemoteException
  {
    Parcel localParcel1 = Parcel.obtain();
    Parcel localParcel2 = Parcel.obtain();
    try
    {
      localParcel1.writeInterfaceToken("com.google.android.gms.ads.internal.reward.client.IRewardedVideoAdListener");
      zznJ.transact(1, localParcel1, localParcel2, 0);
      localParcel2.readException();
      return;
    }
    finally
    {
      localParcel2.recycle();
      localParcel1.recycle();
    }
  }
  
  public void onRewardedVideoAdOpened()
    throws RemoteException
  {
    Parcel localParcel1 = Parcel.obtain();
    Parcel localParcel2 = Parcel.obtain();
    try
    {
      localParcel1.writeInterfaceToken("com.google.android.gms.ads.internal.reward.client.IRewardedVideoAdListener");
      zznJ.transact(2, localParcel1, localParcel2, 0);
      localParcel2.readException();
      return;
    }
    finally
    {
      localParcel2.recycle();
      localParcel1.recycle();
    }
  }
  
  public void onRewardedVideoStarted()
    throws RemoteException
  {
    Parcel localParcel1 = Parcel.obtain();
    Parcel localParcel2 = Parcel.obtain();
    try
    {
      localParcel1.writeInterfaceToken("com.google.android.gms.ads.internal.reward.client.IRewardedVideoAdListener");
      zznJ.transact(3, localParcel1, localParcel2, 0);
      localParcel2.readException();
      return;
    }
    finally
    {
      localParcel2.recycle();
      localParcel1.recycle();
    }
  }
  
  /* Error */
  public void zza(zza paramzza)
    throws RemoteException
  {
    // Byte code:
    //   0: invokestatic 30	android/os/Parcel:obtain	()Landroid/os/Parcel;
    //   3: astore_2
    //   4: invokestatic 30	android/os/Parcel:obtain	()Landroid/os/Parcel;
    //   7: astore_3
    //   8: aload_2
    //   9: ldc 32
    //   11: invokevirtual 36	android/os/Parcel:writeInterfaceToken	(Ljava/lang/String;)V
    //   14: aload_1
    //   15: ifnull +42 -> 57
    //   18: aload_1
    //   19: invokeinterface 63 1 0
    //   24: astore_1
    //   25: aload_2
    //   26: aload_1
    //   27: invokevirtual 66	android/os/Parcel:writeStrongBinder	(Landroid/os/IBinder;)V
    //   30: aload_0
    //   31: getfield 18	com/google/android/gms/ads/internal/reward/client/zzd$zza$zza:zznJ	Landroid/os/IBinder;
    //   34: iconst_5
    //   35: aload_2
    //   36: aload_3
    //   37: iconst_0
    //   38: invokeinterface 42 5 0
    //   43: pop
    //   44: aload_3
    //   45: invokevirtual 45	android/os/Parcel:readException	()V
    //   48: aload_3
    //   49: invokevirtual 48	android/os/Parcel:recycle	()V
    //   52: aload_2
    //   53: invokevirtual 48	android/os/Parcel:recycle	()V
    //   56: return
    //   57: aconst_null
    //   58: astore_1
    //   59: goto -34 -> 25
    //   62: astore_1
    //   63: aload_3
    //   64: invokevirtual 48	android/os/Parcel:recycle	()V
    //   67: aload_2
    //   68: invokevirtual 48	android/os/Parcel:recycle	()V
    //   71: aload_1
    //   72: athrow
    // Local variable table:
    //   start	length	slot	name	signature
    //   0	73	0	this	zza
    //   0	73	1	paramzza	zza
    //   3	65	2	localParcel1	Parcel
    //   7	57	3	localParcel2	Parcel
    // Exception table:
    //   from	to	target	type
    //   8	14	62	finally
    //   18	25	62	finally
    //   25	48	62	finally
  }
}

/* Location:
 * Qualified Name:     com.google.android.gms.ads.internal.reward.client.zzd.zza.zza
 * Java Class Version: 6 (50.0)
 * JD-Core Version:    0.7.1
 */