package com.google.android.gms.dynamic;

import android.os.IBinder;
import android.os.Parcel;
import android.os.RemoteException;

class zzc$zza$zza
  implements zzc
{
  private IBinder zznJ;
  
  zzc$zza$zza(IBinder paramIBinder)
  {
    zznJ = paramIBinder;
  }
  
  public IBinder asBinder()
  {
    return zznJ;
  }
  
  /* Error */
  public android.os.Bundle getArguments()
    throws RemoteException
  {
    // Byte code:
    //   0: invokestatic 31	android/os/Parcel:obtain	()Landroid/os/Parcel;
    //   3: astore_2
    //   4: invokestatic 31	android/os/Parcel:obtain	()Landroid/os/Parcel;
    //   7: astore_3
    //   8: aload_2
    //   9: ldc 33
    //   11: invokevirtual 37	android/os/Parcel:writeInterfaceToken	(Ljava/lang/String;)V
    //   14: aload_0
    //   15: getfield 18	com/google/android/gms/dynamic/zzc$zza$zza:zznJ	Landroid/os/IBinder;
    //   18: iconst_3
    //   19: aload_2
    //   20: aload_3
    //   21: iconst_0
    //   22: invokeinterface 43 5 0
    //   27: pop
    //   28: aload_3
    //   29: invokevirtual 46	android/os/Parcel:readException	()V
    //   32: aload_3
    //   33: invokevirtual 50	android/os/Parcel:readInt	()I
    //   36: ifeq +26 -> 62
    //   39: getstatic 56	android/os/Bundle:CREATOR	Landroid/os/Parcelable$Creator;
    //   42: aload_3
    //   43: invokeinterface 62 2 0
    //   48: checkcast 52	android/os/Bundle
    //   51: astore_1
    //   52: aload_3
    //   53: invokevirtual 65	android/os/Parcel:recycle	()V
    //   56: aload_2
    //   57: invokevirtual 65	android/os/Parcel:recycle	()V
    //   60: aload_1
    //   61: areturn
    //   62: aconst_null
    //   63: astore_1
    //   64: goto -12 -> 52
    //   67: astore_1
    //   68: aload_3
    //   69: invokevirtual 65	android/os/Parcel:recycle	()V
    //   72: aload_2
    //   73: invokevirtual 65	android/os/Parcel:recycle	()V
    //   76: aload_1
    //   77: athrow
    // Local variable table:
    //   start	length	slot	name	signature
    //   0	78	0	this	zza
    //   51	13	1	localBundle	android.os.Bundle
    //   67	10	1	localObject	Object
    //   3	70	2	localParcel1	Parcel
    //   7	62	3	localParcel2	Parcel
    // Exception table:
    //   from	to	target	type
    //   8	52	67	finally
  }
  
  public int getId()
    throws RemoteException
  {
    Parcel localParcel1 = Parcel.obtain();
    Parcel localParcel2 = Parcel.obtain();
    try
    {
      localParcel1.writeInterfaceToken("com.google.android.gms.dynamic.IFragmentWrapper");
      zznJ.transact(4, localParcel1, localParcel2, 0);
      localParcel2.readException();
      int i = localParcel2.readInt();
      return i;
    }
    finally
    {
      localParcel2.recycle();
      localParcel1.recycle();
    }
  }
  
  public boolean getRetainInstance()
    throws RemoteException
  {
    boolean bool = false;
    Parcel localParcel1 = Parcel.obtain();
    Parcel localParcel2 = Parcel.obtain();
    try
    {
      localParcel1.writeInterfaceToken("com.google.android.gms.dynamic.IFragmentWrapper");
      zznJ.transact(7, localParcel1, localParcel2, 0);
      localParcel2.readException();
      int i = localParcel2.readInt();
      if (i != 0) {
        bool = true;
      }
      return bool;
    }
    finally
    {
      localParcel2.recycle();
      localParcel1.recycle();
    }
  }
  
  public String getTag()
    throws RemoteException
  {
    Parcel localParcel1 = Parcel.obtain();
    Parcel localParcel2 = Parcel.obtain();
    try
    {
      localParcel1.writeInterfaceToken("com.google.android.gms.dynamic.IFragmentWrapper");
      zznJ.transact(8, localParcel1, localParcel2, 0);
      localParcel2.readException();
      String str = localParcel2.readString();
      return str;
    }
    finally
    {
      localParcel2.recycle();
      localParcel1.recycle();
    }
  }
  
  public int getTargetRequestCode()
    throws RemoteException
  {
    Parcel localParcel1 = Parcel.obtain();
    Parcel localParcel2 = Parcel.obtain();
    try
    {
      localParcel1.writeInterfaceToken("com.google.android.gms.dynamic.IFragmentWrapper");
      zznJ.transact(10, localParcel1, localParcel2, 0);
      localParcel2.readException();
      int i = localParcel2.readInt();
      return i;
    }
    finally
    {
      localParcel2.recycle();
      localParcel1.recycle();
    }
  }
  
  public boolean getUserVisibleHint()
    throws RemoteException
  {
    boolean bool = false;
    Parcel localParcel1 = Parcel.obtain();
    Parcel localParcel2 = Parcel.obtain();
    try
    {
      localParcel1.writeInterfaceToken("com.google.android.gms.dynamic.IFragmentWrapper");
      zznJ.transact(11, localParcel1, localParcel2, 0);
      localParcel2.readException();
      int i = localParcel2.readInt();
      if (i != 0) {
        bool = true;
      }
      return bool;
    }
    finally
    {
      localParcel2.recycle();
      localParcel1.recycle();
    }
  }
  
  public zzd getView()
    throws RemoteException
  {
    Parcel localParcel1 = Parcel.obtain();
    Parcel localParcel2 = Parcel.obtain();
    try
    {
      localParcel1.writeInterfaceToken("com.google.android.gms.dynamic.IFragmentWrapper");
      zznJ.transact(12, localParcel1, localParcel2, 0);
      localParcel2.readException();
      zzd localzzd = zzd.zza.zzbk(localParcel2.readStrongBinder());
      return localzzd;
    }
    finally
    {
      localParcel2.recycle();
      localParcel1.recycle();
    }
  }
  
  public boolean isAdded()
    throws RemoteException
  {
    boolean bool = false;
    Parcel localParcel1 = Parcel.obtain();
    Parcel localParcel2 = Parcel.obtain();
    try
    {
      localParcel1.writeInterfaceToken("com.google.android.gms.dynamic.IFragmentWrapper");
      zznJ.transact(13, localParcel1, localParcel2, 0);
      localParcel2.readException();
      int i = localParcel2.readInt();
      if (i != 0) {
        bool = true;
      }
      return bool;
    }
    finally
    {
      localParcel2.recycle();
      localParcel1.recycle();
    }
  }
  
  public boolean isDetached()
    throws RemoteException
  {
    boolean bool = false;
    Parcel localParcel1 = Parcel.obtain();
    Parcel localParcel2 = Parcel.obtain();
    try
    {
      localParcel1.writeInterfaceToken("com.google.android.gms.dynamic.IFragmentWrapper");
      zznJ.transact(14, localParcel1, localParcel2, 0);
      localParcel2.readException();
      int i = localParcel2.readInt();
      if (i != 0) {
        bool = true;
      }
      return bool;
    }
    finally
    {
      localParcel2.recycle();
      localParcel1.recycle();
    }
  }
  
  public boolean isHidden()
    throws RemoteException
  {
    boolean bool = false;
    Parcel localParcel1 = Parcel.obtain();
    Parcel localParcel2 = Parcel.obtain();
    try
    {
      localParcel1.writeInterfaceToken("com.google.android.gms.dynamic.IFragmentWrapper");
      zznJ.transact(15, localParcel1, localParcel2, 0);
      localParcel2.readException();
      int i = localParcel2.readInt();
      if (i != 0) {
        bool = true;
      }
      return bool;
    }
    finally
    {
      localParcel2.recycle();
      localParcel1.recycle();
    }
  }
  
  public boolean isInLayout()
    throws RemoteException
  {
    boolean bool = false;
    Parcel localParcel1 = Parcel.obtain();
    Parcel localParcel2 = Parcel.obtain();
    try
    {
      localParcel1.writeInterfaceToken("com.google.android.gms.dynamic.IFragmentWrapper");
      zznJ.transact(16, localParcel1, localParcel2, 0);
      localParcel2.readException();
      int i = localParcel2.readInt();
      if (i != 0) {
        bool = true;
      }
      return bool;
    }
    finally
    {
      localParcel2.recycle();
      localParcel1.recycle();
    }
  }
  
  public boolean isRemoving()
    throws RemoteException
  {
    boolean bool = false;
    Parcel localParcel1 = Parcel.obtain();
    Parcel localParcel2 = Parcel.obtain();
    try
    {
      localParcel1.writeInterfaceToken("com.google.android.gms.dynamic.IFragmentWrapper");
      zznJ.transact(17, localParcel1, localParcel2, 0);
      localParcel2.readException();
      int i = localParcel2.readInt();
      if (i != 0) {
        bool = true;
      }
      return bool;
    }
    finally
    {
      localParcel2.recycle();
      localParcel1.recycle();
    }
  }
  
  public boolean isResumed()
    throws RemoteException
  {
    boolean bool = false;
    Parcel localParcel1 = Parcel.obtain();
    Parcel localParcel2 = Parcel.obtain();
    try
    {
      localParcel1.writeInterfaceToken("com.google.android.gms.dynamic.IFragmentWrapper");
      zznJ.transact(18, localParcel1, localParcel2, 0);
      localParcel2.readException();
      int i = localParcel2.readInt();
      if (i != 0) {
        bool = true;
      }
      return bool;
    }
    finally
    {
      localParcel2.recycle();
      localParcel1.recycle();
    }
  }
  
  public boolean isVisible()
    throws RemoteException
  {
    boolean bool = false;
    Parcel localParcel1 = Parcel.obtain();
    Parcel localParcel2 = Parcel.obtain();
    try
    {
      localParcel1.writeInterfaceToken("com.google.android.gms.dynamic.IFragmentWrapper");
      zznJ.transact(19, localParcel1, localParcel2, 0);
      localParcel2.readException();
      int i = localParcel2.readInt();
      if (i != 0) {
        bool = true;
      }
      return bool;
    }
    finally
    {
      localParcel2.recycle();
      localParcel1.recycle();
    }
  }
  
  public void setHasOptionsMenu(boolean paramBoolean)
    throws RemoteException
  {
    int i = 0;
    Parcel localParcel1 = Parcel.obtain();
    Parcel localParcel2 = Parcel.obtain();
    try
    {
      localParcel1.writeInterfaceToken("com.google.android.gms.dynamic.IFragmentWrapper");
      if (paramBoolean) {
        i = 1;
      }
      localParcel1.writeInt(i);
      zznJ.transact(21, localParcel1, localParcel2, 0);
      localParcel2.readException();
      return;
    }
    finally
    {
      localParcel2.recycle();
      localParcel1.recycle();
    }
  }
  
  public void setMenuVisibility(boolean paramBoolean)
    throws RemoteException
  {
    int i = 0;
    Parcel localParcel1 = Parcel.obtain();
    Parcel localParcel2 = Parcel.obtain();
    try
    {
      localParcel1.writeInterfaceToken("com.google.android.gms.dynamic.IFragmentWrapper");
      if (paramBoolean) {
        i = 1;
      }
      localParcel1.writeInt(i);
      zznJ.transact(22, localParcel1, localParcel2, 0);
      localParcel2.readException();
      return;
    }
    finally
    {
      localParcel2.recycle();
      localParcel1.recycle();
    }
  }
  
  public void setRetainInstance(boolean paramBoolean)
    throws RemoteException
  {
    int i = 0;
    Parcel localParcel1 = Parcel.obtain();
    Parcel localParcel2 = Parcel.obtain();
    try
    {
      localParcel1.writeInterfaceToken("com.google.android.gms.dynamic.IFragmentWrapper");
      if (paramBoolean) {
        i = 1;
      }
      localParcel1.writeInt(i);
      zznJ.transact(23, localParcel1, localParcel2, 0);
      localParcel2.readException();
      return;
    }
    finally
    {
      localParcel2.recycle();
      localParcel1.recycle();
    }
  }
  
  public void setUserVisibleHint(boolean paramBoolean)
    throws RemoteException
  {
    int i = 0;
    Parcel localParcel1 = Parcel.obtain();
    Parcel localParcel2 = Parcel.obtain();
    try
    {
      localParcel1.writeInterfaceToken("com.google.android.gms.dynamic.IFragmentWrapper");
      if (paramBoolean) {
        i = 1;
      }
      localParcel1.writeInt(i);
      zznJ.transact(24, localParcel1, localParcel2, 0);
      localParcel2.readException();
      return;
    }
    finally
    {
      localParcel2.recycle();
      localParcel1.recycle();
    }
  }
  
  /* Error */
  public void startActivity(android.content.Intent paramIntent)
    throws RemoteException
  {
    // Byte code:
    //   0: invokestatic 31	android/os/Parcel:obtain	()Landroid/os/Parcel;
    //   3: astore_2
    //   4: invokestatic 31	android/os/Parcel:obtain	()Landroid/os/Parcel;
    //   7: astore_3
    //   8: aload_2
    //   9: ldc 33
    //   11: invokevirtual 37	android/os/Parcel:writeInterfaceToken	(Ljava/lang/String;)V
    //   14: aload_1
    //   15: ifnull +42 -> 57
    //   18: aload_2
    //   19: iconst_1
    //   20: invokevirtual 100	android/os/Parcel:writeInt	(I)V
    //   23: aload_1
    //   24: aload_2
    //   25: iconst_0
    //   26: invokevirtual 111	android/content/Intent:writeToParcel	(Landroid/os/Parcel;I)V
    //   29: aload_0
    //   30: getfield 18	com/google/android/gms/dynamic/zzc$zza$zza:zznJ	Landroid/os/IBinder;
    //   33: bipush 25
    //   35: aload_2
    //   36: aload_3
    //   37: iconst_0
    //   38: invokeinterface 43 5 0
    //   43: pop
    //   44: aload_3
    //   45: invokevirtual 46	android/os/Parcel:readException	()V
    //   48: aload_3
    //   49: invokevirtual 65	android/os/Parcel:recycle	()V
    //   52: aload_2
    //   53: invokevirtual 65	android/os/Parcel:recycle	()V
    //   56: return
    //   57: aload_2
    //   58: iconst_0
    //   59: invokevirtual 100	android/os/Parcel:writeInt	(I)V
    //   62: goto -33 -> 29
    //   65: astore_1
    //   66: aload_3
    //   67: invokevirtual 65	android/os/Parcel:recycle	()V
    //   70: aload_2
    //   71: invokevirtual 65	android/os/Parcel:recycle	()V
    //   74: aload_1
    //   75: athrow
    // Local variable table:
    //   start	length	slot	name	signature
    //   0	76	0	this	zza
    //   0	76	1	paramIntent	android.content.Intent
    //   3	68	2	localParcel1	Parcel
    //   7	60	3	localParcel2	Parcel
    // Exception table:
    //   from	to	target	type
    //   8	14	65	finally
    //   18	29	65	finally
    //   29	48	65	finally
    //   57	62	65	finally
  }
  
  /* Error */
  public void startActivityForResult(android.content.Intent paramIntent, int paramInt)
    throws RemoteException
  {
    // Byte code:
    //   0: invokestatic 31	android/os/Parcel:obtain	()Landroid/os/Parcel;
    //   3: astore_3
    //   4: invokestatic 31	android/os/Parcel:obtain	()Landroid/os/Parcel;
    //   7: astore 4
    //   9: aload_3
    //   10: ldc 33
    //   12: invokevirtual 37	android/os/Parcel:writeInterfaceToken	(Ljava/lang/String;)V
    //   15: aload_1
    //   16: ifnull +50 -> 66
    //   19: aload_3
    //   20: iconst_1
    //   21: invokevirtual 100	android/os/Parcel:writeInt	(I)V
    //   24: aload_1
    //   25: aload_3
    //   26: iconst_0
    //   27: invokevirtual 111	android/content/Intent:writeToParcel	(Landroid/os/Parcel;I)V
    //   30: aload_3
    //   31: iload_2
    //   32: invokevirtual 100	android/os/Parcel:writeInt	(I)V
    //   35: aload_0
    //   36: getfield 18	com/google/android/gms/dynamic/zzc$zza$zza:zznJ	Landroid/os/IBinder;
    //   39: bipush 26
    //   41: aload_3
    //   42: aload 4
    //   44: iconst_0
    //   45: invokeinterface 43 5 0
    //   50: pop
    //   51: aload 4
    //   53: invokevirtual 46	android/os/Parcel:readException	()V
    //   56: aload 4
    //   58: invokevirtual 65	android/os/Parcel:recycle	()V
    //   61: aload_3
    //   62: invokevirtual 65	android/os/Parcel:recycle	()V
    //   65: return
    //   66: aload_3
    //   67: iconst_0
    //   68: invokevirtual 100	android/os/Parcel:writeInt	(I)V
    //   71: goto -41 -> 30
    //   74: astore_1
    //   75: aload 4
    //   77: invokevirtual 65	android/os/Parcel:recycle	()V
    //   80: aload_3
    //   81: invokevirtual 65	android/os/Parcel:recycle	()V
    //   84: aload_1
    //   85: athrow
    // Local variable table:
    //   start	length	slot	name	signature
    //   0	86	0	this	zza
    //   0	86	1	paramIntent	android.content.Intent
    //   0	86	2	paramInt	int
    //   3	78	3	localParcel1	Parcel
    //   7	69	4	localParcel2	Parcel
    // Exception table:
    //   from	to	target	type
    //   9	15	74	finally
    //   19	30	74	finally
    //   30	56	74	finally
    //   66	71	74	finally
  }
  
  /* Error */
  public void zzn(zzd paramzzd)
    throws RemoteException
  {
    // Byte code:
    //   0: invokestatic 31	android/os/Parcel:obtain	()Landroid/os/Parcel;
    //   3: astore_2
    //   4: invokestatic 31	android/os/Parcel:obtain	()Landroid/os/Parcel;
    //   7: astore_3
    //   8: aload_2
    //   9: ldc 33
    //   11: invokevirtual 37	android/os/Parcel:writeInterfaceToken	(Ljava/lang/String;)V
    //   14: aload_1
    //   15: ifnull +43 -> 58
    //   18: aload_1
    //   19: invokeinterface 119 1 0
    //   24: astore_1
    //   25: aload_2
    //   26: aload_1
    //   27: invokevirtual 122	android/os/Parcel:writeStrongBinder	(Landroid/os/IBinder;)V
    //   30: aload_0
    //   31: getfield 18	com/google/android/gms/dynamic/zzc$zza$zza:zznJ	Landroid/os/IBinder;
    //   34: bipush 20
    //   36: aload_2
    //   37: aload_3
    //   38: iconst_0
    //   39: invokeinterface 43 5 0
    //   44: pop
    //   45: aload_3
    //   46: invokevirtual 46	android/os/Parcel:readException	()V
    //   49: aload_3
    //   50: invokevirtual 65	android/os/Parcel:recycle	()V
    //   53: aload_2
    //   54: invokevirtual 65	android/os/Parcel:recycle	()V
    //   57: return
    //   58: aconst_null
    //   59: astore_1
    //   60: goto -35 -> 25
    //   63: astore_1
    //   64: aload_3
    //   65: invokevirtual 65	android/os/Parcel:recycle	()V
    //   68: aload_2
    //   69: invokevirtual 65	android/os/Parcel:recycle	()V
    //   72: aload_1
    //   73: athrow
    // Local variable table:
    //   start	length	slot	name	signature
    //   0	74	0	this	zza
    //   0	74	1	paramzzd	zzd
    //   3	66	2	localParcel1	Parcel
    //   7	58	3	localParcel2	Parcel
    // Exception table:
    //   from	to	target	type
    //   8	14	63	finally
    //   18	25	63	finally
    //   25	49	63	finally
  }
  
  /* Error */
  public void zzo(zzd paramzzd)
    throws RemoteException
  {
    // Byte code:
    //   0: invokestatic 31	android/os/Parcel:obtain	()Landroid/os/Parcel;
    //   3: astore_2
    //   4: invokestatic 31	android/os/Parcel:obtain	()Landroid/os/Parcel;
    //   7: astore_3
    //   8: aload_2
    //   9: ldc 33
    //   11: invokevirtual 37	android/os/Parcel:writeInterfaceToken	(Ljava/lang/String;)V
    //   14: aload_1
    //   15: ifnull +43 -> 58
    //   18: aload_1
    //   19: invokeinterface 119 1 0
    //   24: astore_1
    //   25: aload_2
    //   26: aload_1
    //   27: invokevirtual 122	android/os/Parcel:writeStrongBinder	(Landroid/os/IBinder;)V
    //   30: aload_0
    //   31: getfield 18	com/google/android/gms/dynamic/zzc$zza$zza:zznJ	Landroid/os/IBinder;
    //   34: bipush 27
    //   36: aload_2
    //   37: aload_3
    //   38: iconst_0
    //   39: invokeinterface 43 5 0
    //   44: pop
    //   45: aload_3
    //   46: invokevirtual 46	android/os/Parcel:readException	()V
    //   49: aload_3
    //   50: invokevirtual 65	android/os/Parcel:recycle	()V
    //   53: aload_2
    //   54: invokevirtual 65	android/os/Parcel:recycle	()V
    //   57: return
    //   58: aconst_null
    //   59: astore_1
    //   60: goto -35 -> 25
    //   63: astore_1
    //   64: aload_3
    //   65: invokevirtual 65	android/os/Parcel:recycle	()V
    //   68: aload_2
    //   69: invokevirtual 65	android/os/Parcel:recycle	()V
    //   72: aload_1
    //   73: athrow
    // Local variable table:
    //   start	length	slot	name	signature
    //   0	74	0	this	zza
    //   0	74	1	paramzzd	zzd
    //   3	66	2	localParcel1	Parcel
    //   7	58	3	localParcel2	Parcel
    // Exception table:
    //   from	to	target	type
    //   8	14	63	finally
    //   18	25	63	finally
    //   25	49	63	finally
  }
  
  public zzd zzsa()
    throws RemoteException
  {
    Parcel localParcel1 = Parcel.obtain();
    Parcel localParcel2 = Parcel.obtain();
    try
    {
      localParcel1.writeInterfaceToken("com.google.android.gms.dynamic.IFragmentWrapper");
      zznJ.transact(2, localParcel1, localParcel2, 0);
      localParcel2.readException();
      zzd localzzd = zzd.zza.zzbk(localParcel2.readStrongBinder());
      return localzzd;
    }
    finally
    {
      localParcel2.recycle();
      localParcel1.recycle();
    }
  }
  
  public zzc zzsb()
    throws RemoteException
  {
    Parcel localParcel1 = Parcel.obtain();
    Parcel localParcel2 = Parcel.obtain();
    try
    {
      localParcel1.writeInterfaceToken("com.google.android.gms.dynamic.IFragmentWrapper");
      zznJ.transact(5, localParcel1, localParcel2, 0);
      localParcel2.readException();
      zzc localzzc = zzc.zza.zzbj(localParcel2.readStrongBinder());
      return localzzc;
    }
    finally
    {
      localParcel2.recycle();
      localParcel1.recycle();
    }
  }
  
  public zzd zzsc()
    throws RemoteException
  {
    Parcel localParcel1 = Parcel.obtain();
    Parcel localParcel2 = Parcel.obtain();
    try
    {
      localParcel1.writeInterfaceToken("com.google.android.gms.dynamic.IFragmentWrapper");
      zznJ.transact(6, localParcel1, localParcel2, 0);
      localParcel2.readException();
      zzd localzzd = zzd.zza.zzbk(localParcel2.readStrongBinder());
      return localzzd;
    }
    finally
    {
      localParcel2.recycle();
      localParcel1.recycle();
    }
  }
  
  public zzc zzsd()
    throws RemoteException
  {
    Parcel localParcel1 = Parcel.obtain();
    Parcel localParcel2 = Parcel.obtain();
    try
    {
      localParcel1.writeInterfaceToken("com.google.android.gms.dynamic.IFragmentWrapper");
      zznJ.transact(9, localParcel1, localParcel2, 0);
      localParcel2.readException();
      zzc localzzc = zzc.zza.zzbj(localParcel2.readStrongBinder());
      return localzzc;
    }
    finally
    {
      localParcel2.recycle();
      localParcel1.recycle();
    }
  }
}

/* Location:
 * Qualified Name:     com.google.android.gms.dynamic.zzc.zza.zza
 * Java Class Version: 6 (50.0)
 * JD-Core Version:    0.7.1
 */