package crittercism.android;

final class ec$1
  implements Runnable
{
  ec$1(ec paramec, Throwable paramThrowable, long paramLong) {}
  
  /* Error */
  public final void run()
  {
    // Byte code:
    //   0: aload_0
    //   1: getfield 18	crittercism/android/ec$1:c	Lcrittercism/android/ec;
    //   4: getfield 37	crittercism/android/ec:d	Lcrittercism/android/dw;
    //   7: invokevirtual 42	crittercism/android/dw:b	()Z
    //   10: ifeq +4 -> 14
    //   13: return
    //   14: new 44	crittercism/android/bk
    //   17: dup
    //   18: aload_0
    //   19: getfield 20	crittercism/android/ec$1:a	Ljava/lang/Throwable;
    //   22: aload_0
    //   23: getfield 22	crittercism/android/ec$1:b	J
    //   26: invokespecial 47	crittercism/android/bk:<init>	(Ljava/lang/Throwable;J)V
    //   29: astore_1
    //   30: aload_1
    //   31: ldc 49
    //   33: putfield 53	crittercism/android/bk:f	Ljava/lang/String;
    //   36: aload_1
    //   37: getfield 57	crittercism/android/bk:g	Lorg/json/JSONObject;
    //   40: ldc 59
    //   42: ldc 61
    //   44: invokevirtual 67	org/json/JSONObject:put	(Ljava/lang/String;Ljava/lang/Object;)Lorg/json/JSONObject;
    //   47: pop
    //   48: aload_1
    //   49: getfield 57	crittercism/android/bk:g	Lorg/json/JSONObject;
    //   52: ldc 69
    //   54: invokevirtual 73	org/json/JSONObject:remove	(Ljava/lang/String;)Ljava/lang/Object;
    //   57: pop
    //   58: aload_0
    //   59: getfield 18	crittercism/android/ec$1:c	Lcrittercism/android/ec;
    //   62: getfield 76	crittercism/android/ec:a	Lcrittercism/android/aw;
    //   65: invokeinterface 82 1 0
    //   70: aload_1
    //   71: invokevirtual 87	crittercism/android/bs:a	(Lcrittercism/android/ch;)Z
    //   74: pop
    //   75: return
    //   76: astore_1
    //   77: return
    //   78: astore_1
    //   79: aload_0
    //   80: getfield 18	crittercism/android/ec$1:c	Lcrittercism/android/ec;
    //   83: astore_1
    //   84: aload_0
    //   85: getfield 20	crittercism/android/ec$1:a	Ljava/lang/Throwable;
    //   88: astore_1
    //   89: return
    //   90: astore_2
    //   91: goto -43 -> 48
    // Local variable table:
    //   start	length	slot	name	signature
    //   0	94	0	this	1
    //   29	42	1	localbk	bk
    //   76	1	1	localThreadDeath	ThreadDeath
    //   78	1	1	localThrowable	Throwable
    //   83	6	1	localObject	Object
    //   90	1	2	localJSONException	org.json.JSONException
    // Exception table:
    //   from	to	target	type
    //   0	13	76	java/lang/ThreadDeath
    //   14	36	76	java/lang/ThreadDeath
    //   36	48	76	java/lang/ThreadDeath
    //   48	75	76	java/lang/ThreadDeath
    //   0	13	78	java/lang/Throwable
    //   14	36	78	java/lang/Throwable
    //   36	48	78	java/lang/Throwable
    //   48	75	78	java/lang/Throwable
    //   36	48	90	org/json/JSONException
  }
}

/* Location:
 * Qualified Name:     crittercism.android.ec.1
 * Java Class Version: 6 (50.0)
 * JD-Core Version:    0.7.1
 */