package com.google.android.gms.internal;

import android.os.IBinder;
import android.os.Parcel;
import android.os.RemoteException;

class zzft$zza$zza
  implements zzft
{
  private IBinder zznJ;
  
  zzft$zza$zza(IBinder paramIBinder)
  {
    zznJ = paramIBinder;
  }
  
  public IBinder asBinder()
  {
    return zznJ;
  }
  
  /* Error */
  public void onActivityResult(int paramInt1, int paramInt2, android.content.Intent paramIntent)
    throws RemoteException
  {
    // Byte code:
    //   0: invokestatic 31	android/os/Parcel:obtain	()Landroid/os/Parcel;
    //   3: astore 4
    //   5: invokestatic 31	android/os/Parcel:obtain	()Landroid/os/Parcel;
    //   8: astore 5
    //   10: aload 4
    //   12: ldc 33
    //   14: invokevirtual 37	android/os/Parcel:writeInterfaceToken	(Ljava/lang/String;)V
    //   17: aload 4
    //   19: iload_1
    //   20: invokevirtual 41	android/os/Parcel:writeInt	(I)V
    //   23: aload 4
    //   25: iload_2
    //   26: invokevirtual 41	android/os/Parcel:writeInt	(I)V
    //   29: aload_3
    //   30: ifnull +48 -> 78
    //   33: aload 4
    //   35: iconst_1
    //   36: invokevirtual 41	android/os/Parcel:writeInt	(I)V
    //   39: aload_3
    //   40: aload 4
    //   42: iconst_0
    //   43: invokevirtual 47	android/content/Intent:writeToParcel	(Landroid/os/Parcel;I)V
    //   46: aload_0
    //   47: getfield 18	com/google/android/gms/internal/zzft$zza$zza:zznJ	Landroid/os/IBinder;
    //   50: iconst_3
    //   51: aload 4
    //   53: aload 5
    //   55: iconst_0
    //   56: invokeinterface 53 5 0
    //   61: pop
    //   62: aload 5
    //   64: invokevirtual 56	android/os/Parcel:readException	()V
    //   67: aload 5
    //   69: invokevirtual 59	android/os/Parcel:recycle	()V
    //   72: aload 4
    //   74: invokevirtual 59	android/os/Parcel:recycle	()V
    //   77: return
    //   78: aload 4
    //   80: iconst_0
    //   81: invokevirtual 41	android/os/Parcel:writeInt	(I)V
    //   84: goto -38 -> 46
    //   87: astore_3
    //   88: aload 5
    //   90: invokevirtual 59	android/os/Parcel:recycle	()V
    //   93: aload 4
    //   95: invokevirtual 59	android/os/Parcel:recycle	()V
    //   98: aload_3
    //   99: athrow
    // Local variable table:
    //   start	length	slot	name	signature
    //   0	100	0	this	zza
    //   0	100	1	paramInt1	int
    //   0	100	2	paramInt2	int
    //   0	100	3	paramIntent	android.content.Intent
    //   3	91	4	localParcel1	Parcel
    //   8	81	5	localParcel2	Parcel
    // Exception table:
    //   from	to	target	type
    //   10	29	87	finally
    //   33	46	87	finally
    //   46	67	87	finally
    //   78	84	87	finally
  }
  
  public void onCreate()
    throws RemoteException
  {
    Parcel localParcel1 = Parcel.obtain();
    Parcel localParcel2 = Parcel.obtain();
    try
    {
      localParcel1.writeInterfaceToken("com.google.android.gms.ads.internal.purchase.client.IInAppPurchaseManager");
      zznJ.transact(1, localParcel1, localParcel2, 0);
      localParcel2.readException();
      return;
    }
    finally
    {
      localParcel2.recycle();
      localParcel1.recycle();
    }
  }
  
  public void onDestroy()
    throws RemoteException
  {
    Parcel localParcel1 = Parcel.obtain();
    Parcel localParcel2 = Parcel.obtain();
    try
    {
      localParcel1.writeInterfaceToken("com.google.android.gms.ads.internal.purchase.client.IInAppPurchaseManager");
      zznJ.transact(2, localParcel1, localParcel2, 0);
      localParcel2.readException();
      return;
    }
    finally
    {
      localParcel2.recycle();
      localParcel1.recycle();
    }
  }
}

/* Location:
 * Qualified Name:     com.google.android.gms.internal.zzft.zza.zza
 * Java Class Version: 6 (50.0)
 * JD-Core Version:    0.7.1
 */